{
  "id": "1977194412713",
  "url": "https://www.eventbrite.com/e/exploration-of-god-passes-by-with-dr-william-maxwell-registration-1977194412713",
  "name": "Exploration of \"God Passes By\" with Dr. William Maxwell",
  "shortDescription": "This workshop, focuses on \"The First Ten Lessons\" of God Passes By, unveiling the predictive theory of history latent in this great",
  "startDate": "2026-01-09T16:00:00-0800",
  "endDate": "2026-01-11T14:00:00-0800",
  "image": "https://drbi.s3.amazonaws.com/events/1977194412713-main.jpg",
  "location": {
    "name": "Desert Rose Baha'i Institute",
    "address": "1950 W William Sears Dr",
    "city": "Eloy",
    "state": "AZ",
    "zip": "85131",
    "latitude": "39.3700973",
    "longitude": "-121.1038655"
  },
  "price": null,
  "organizer": "Desert Rose Baha'i Institute",
  "fullDescription": "This workshop, focuses on \"The First Ten Lessons\" of God Passes By, unveiling the predictive theory of history latent in this great book.",
  "eventSchedule": [],
  "highlights": [
    "In person",
    "Virtual"
  ],
  "refundPolicy": "Refund Policy</p><div class=\"Card_body__vj7ua undefined\">Refunds up to 1 day before event</div></div></div></div></div><dialog class=\"Modal_dialog__1zirs \"><div class=\"Modal_container__1zirs\"><div class=\"Modal_header__1zirs\"><button class=\"Modal_closeButton__1zirs\" aria-label=\"close\"><i class=\"Icon_root__1kdkz Icon_icon-medium__1kdkz\" aria-hidden=\"true\"><svg xmlns=\"http://www.",
  "categories": [],
  "images": [
    "https://img.evbuc.com/https%3A%2F%2Fcdn.evbuc.com%2Fimages%2F1173001641%2F177237344149%2F1%2Foriginal.20251215-185636",
    "https://img.evbuc.com/https%3A%2F%2Fcdn.evbuc.com%2Fimages%2F1173001584%2F177237344149%2F1%2Foriginal.20251215-185548",
    "https://img.evbuc.com/https%3A%2F%2Fcdn.evbuc.com%2Fimages%2F553798659%2F177237344149%2F1%2Foriginal.20230712-175546",
    "https://img.evbuc.com/https%3A%2F%2Fcdn.evbuc.com%2Fimages%2F783253739%2F177237344149%2F1%2Foriginal.20240605-031951",
    "https://cdn.evbuc.com/images/1173001641/177237344149/1/logo.20251215-185636"
  ],
  "teacherImage": "https://drbi.s3.amazonaws.com/events/1977194412713-teacher.jpg",
  "source": "external",
  "externalId": "1977194412713",
  "registrationUrl": "https://www.eventbrite.com/e/exploration-of-god-passes-by-with-dr-william-maxwell-registration-1977194412713",
  "visible": true,
  "featured": false,
  "mainImage": "https://drbi.s3.amazonaws.com/events/1977194412713-main.jpg",
  "originalImage": "https://img.evbuc.com/https%3A%2F%2Fcdn.evbuc.com%2Fimages%2F1173001641%2F177237344149%2F1%2Foriginal.20251215-185636?h=1000&w=2000&auto=format%2Ccompress&q=75&sharp=10&s=4a790c6914a728312b03ca36857890da",
  "lastModified": "ae9a8551ebc115c1c878389c9e6e71c9",
  "lastSynced": "2025-12-16T16:42:00.069Z",
  "scraped": {
    "orgPageDate": "2025-12-23T15:26:54.831Z",
    "detailPageDate": "2025-12-16T16:42:00.069Z"
  }
}